prseq-0.0.32.dist-info/METADATA
prseq-0.0.32.dist-info/WHEEL
prseq-0.0.32.dist-info/entry_points.txt
prseq/__init__.py
prseq/_prseq.cp311-win_amd64.pyd
prseq/args.py
prseq/cli.py
prseq/fasta.py
prseq/fastq.py
prseq/py.typed
prseq-0.0.32.dist-info/RECORD
