Metadata-Version: 2.4
Name: prseq
Version: 0.0.32
Classifier: Programming Language :: Rust
Classifier: Programming Language :: Python :: 3
Classifier: Programming Language :: Python :: 3.10
Classifier: Programming Language :: Python :: 3.11
Classifier: Programming Language :: Python :: 3.12
Classifier: Programming Language :: Python :: 3.13
Classifier: Programming Language :: Python :: 3.14
Classifier: License :: OSI Approved :: MIT License
Classifier: Topic :: Scientific/Engineering :: Bio-Informatics
Requires-Dist: maturin>=1.9.6
Summary: Python tools (backed by Rust) for sequence analysis
Keywords: bioinformatics,fasta,fastq,rust,sequence-analysis
Author-email: "Terry C. Jones" <terence.jones@charite.de>
Requires-Python: >=3.10, <=3.14
Project-URL: Homepage, https://github.com/virologyCharite/prseq
Project-URL: Repository, https://github.com/virologyCharite/prseq
